celery_context/__init__.py
celery_context/model.py
celery_context/trace_logger.py
celery_context-0.0.3.23092222.dist-info/LICENSE
celery_context-0.0.3.23092222.dist-info/METADATA
celery_context-0.0.3.23092222.dist-info/WHEEL
celery_context-0.0.3.23092222.dist-info/top_level.txt
celery_context-0.0.3.23092222.dist-info/RECORD
