Metadata-Version: 2.1
Name: celery-context
Version: 0.0.3.23092222
Summary: 实现celery在flask/django下的上下文一致性的简单扩展
Home-page: https://github.com/BingerYang/celery_context
Author: binger
Author-email: <xuehen_521@126.com>
Maintainer: binger
Maintainer-email: <xuehen_521@126.com>
Platform: all
Requires-Python: >=3.4
License-File: LICENSE
